drcal/__init__.py
drcal/_poseutils_scipy.py
drcal/bindings.pyi
drcal/bindings.so
drcal/bindings_npsp.pyi
drcal/bindings_npsp.so
drcal/bindings_poseutils_npsp.pyi
drcal/bindings_poseutils_npsp.so
drcal/bindings_triangulation_npsp.pyi
drcal/bindings_triangulation_npsp.so
drcal/cahvor.py
drcal/calibration.py
drcal/calibration_objects.py
drcal/cameramodel.py
drcal/image_transforms.py
drcal/image_utils.py
drcal/model_analysis.py
drcal/poseutils.py
drcal/projections.py
drcal/stereo.py
drcal/synthetic_data.py
drcal/triangulation.py
drcal/utils.py
drcal/visualization.py
drcal.libs/libgfortran-83c28eba.so.5.0.0
drcal.libs/libquadmath-2284e583.so.0.0.0
drcal-0.0.0.dist-info/METADATA
drcal-0.0.0.dist-info/WHEEL
drcal-0.0.0.dist-info/entry_points.txt
drcal-0.0.0.dist-info/RECORD
drcal-0.0.0.dist-info/licenses/LICENSE
