Metadata-Version: 2.1
Name: drcal
Version: 0.0.0
Summary: DrCal for camera calibrations
Author-Email: Robert Leo <robert.leo.jonsson@gmail.com>
Requires-Python: >=3.11
Requires-Dist: fire>=0.7.1
Requires-Dist: gnuplotlib>=0.42
Requires-Dist: matplotlib>=3.10.6
Requires-Dist: numpy<2,>=1.26
Requires-Dist: numpysane>=0.40
Requires-Dist: opencv-contrib-python>=4.11.0.86
Requires-Dist: pybind11>=3.0.1
Requires-Dist: pybind11-stubgen>=2.5.5
Requires-Dist: pyyaml>=6.0.2
Requires-Dist: scipy>=1.16.2
Requires-Dist: setuptools>=80.9.0
Requires-Dist: shapely>=2.1.1
